LICENSE
eqversion/__init__.py
eqversion/eqversion.py
eqversion-0.1.3.dist-info/entry_points.txt
eqversion-0.1.3.dist-info/LICENSE
eqversion-0.1.3.dist-info/WHEEL
eqversion-0.1.3.dist-info/METADATA
eqversion-0.1.3.dist-info/RECORD
