Metadata-Version: 2.1
Name: eqversion
Version: 0.1.3
Summary: EQversion maintains the pyproject.toml and __init__.py (from the main package) versions in the same way.
Home-page: https://github.com/snakypy/eqversion
License: MIT
Keywords: eqversion,snakypy,version,equal,redundancy
Author: William C. Canin
Author-email: william.costa.canin@gmail.com
Requires-Python: >=3.8,<4.0
Classifier: Environment :: Console
Classifier: Intended Audience :: Developers
Classifier: License :: OSI Approved :: MIT License
Classifier: Operating System :: MacOS :: MacOS X
Classifier: Operating System :: Microsoft
Classifier: Operating System :: POSIX :: Linux
Classifier: Operating System :: Unix
Classifier: Programming Language :: Python :: 3
Classifier: Programming Language :: Python :: 3.8
Requires-Dist: click (>=7.1.1,<8.0.0)
Requires-Dist: snakypy (>=0.3.4,<0.4.0)
Requires-Dist: tomlkit (>=0.5.11,<0.6.0)
Project-URL: Bug Tracker, https://github.com/snakypy/eqversion/issues
Project-URL: Repository, https://github.com/snakypy/eqversion
